{
  "timestamp": "20251009_133530",
  "problem": "pdtsp",
  "graph_size": 20,
  "T_max": 3000,
  "val_size": 2,
  "instances": [
    {
      "instance_id": 0,
      "best_cost": 74787.53125,
      "best_path": [
        3,
        17,
        18,
        4,
        13,
        1,
        15,
        5,
        6,
        7,
        9,
        14,
        0,
        10,
        16,
        19,
        12,
        8,
        20,
        2,
        11
      ],
      "path_length": 21,
      "coordinates": [
        [
          0.12717975676059723,
          0.35044172406196594
        ],
        [
          0.6486167311668396,
          0.19067534804344177
        ],
        [
          0.7140422463417053,
          0.0
        ],
        [
          0.9942310452461243,
          0.7915563583374023
        ],
        [
          0.27546873688697815,
          0.13685069978237152
        ],
        [
          0.9606660604476929,
          0.9493924379348755
        ],
        [
          0.9695817232131958,
          0.5003835558891296
        ],
        [
          0.8167037963867188,
          0.16464154422283173
        ],
        [
          0.738691508769989,
          0.01264569815248251
        ],
        [
          0.7002753615379333,
          0.2016877382993698
        ],
        [
          0.5304837822914124,
          0.18124675750732422
        ],
        [
          1.0,
          1.0
        ],
        [
          0.45089811086654663,
          0.21779800951480865
        ],
        [
          0.0,
          0.40478605031967163
        ],
        [
          0.5008522272109985,
          0.8367937803268433
        ],
        [
          0.0690966323018074,
          0.34373530745506287
        ],
        [
          0.19929198920726776,
          0.48444652557373047
        ],
        [
          0.4860364496707916,
          0.4448266327381134
        ],
        [
          0.9246099591255188,
          0.6383726596832275
        ],
        [
          0.34194308519363403,
          0.7128115296363831
        ],
        [
          0.10489051789045334,
          0.4058501720428467
        ]
      ]
    },
    {
      "instance_id": 1,
      "best_cost": 1000086208.0,
      "best_path": [
        8,
        5,
        20,
        13,
        18,
        16,
        1,
        17,
        9,
        4,
        2,
        15,
        19,
        10,
        11,
        3,
        14,
        0,
        6,
        7,
        12
      ],
      "path_length": 21,
      "coordinates": [
        [
          0.8301422595977783,
          0.2689117193222046
        ],
        [
          0.3599562346935272,
          0.14281849563121796
        ],
        [
          0.0,
          0.42020556330680847
        ],
        [
          0.9044037461280823,
          0.9463303685188293
        ],
        [
          0.035968270152807236,
          0.5269813537597656
        ],
        [
          0.7815918922424316,
          0.7522991895675659
        ],
        [
          0.2839168608188629,
          0.7060454487800598
        ],
        [
          0.3410831391811371,
          0.07535389065742493
        ],
        [
          0.9794857501983643,
          0.5513479113578796
        ],
        [
          0.9355853199958801,
          0.5598232746124268
        ],
        [
          0.05908096209168434,
          0.8510729670524597
        ],
        [
          0.7956783175468445,
          0.08527184277772903
        ],
        [
          0.2551969289779663,
          0.0
        ],
        [
          1.0,
          1.0
        ],
        [
          0.8561269044876099,
          0.2160760909318924
        ],
        [
          0.35817834734916687,
          0.41759082674980164
        ],
        [
          0.9161652326583862,
          0.29753854870796204
        ],
        [
          0.8840262293815613,
          0.602628231048584
        ],
        [
          0.7684627771377563,
          0.35129836201667786
        ],
        [
          0.9491247534751892,
          0.5857902765274048
        ],
        [
          0.03801969438791275,
          0.47407808899879456
        ]
      ]
    }
  ]
}